[
    {
        "Date":"2026-05-02",
        "Temperature_C":24.8970084237,
        "Humidity_%":55.440716421,
        "UV_Index":1.3316638107,
        "WindSpeed_m\/s":6.1872493195,
        "Rainfall_mm":2.0210013189,
        "Rain_Probability":18.5,
        "Rain_Alert":"No Rain \u2600\ufe0f"
    },
    {
        "Date":"2026-05-03",
        "Temperature_C":24.9004475417,
        "Humidity_%":55.4304350549,
        "UV_Index":1.3325490035,
        "WindSpeed_m\/s":6.1931876039,
        "Rainfall_mm":2.0101261172,
        "Rain_Probability":18.5,
        "Rain_Alert":"No Rain \u2600\ufe0f"
    },
    {
        "Date":"2026-05-04",
        "Temperature_C":24.9002213295,
        "Humidity_%":55.4335475665,
        "UV_Index":1.33212741,
        "WindSpeed_m\/s":6.1888191766,
        "Rainfall_mm":2.0120848086,
        "Rain_Probability":18.5,
        "Rain_Alert":"No Rain \u2600\ufe0f"
    },
    {
        "Date":"2026-05-05",
        "Temperature_C":24.9012200147,
        "Humidity_%":55.4415250259,
        "UV_Index":1.3322333699,
        "WindSpeed_m\/s":6.1923656673,
        "Rainfall_mm":2.02192705,
        "Rain_Probability":18.5,
        "Rain_Alert":"No Rain \u2600\ufe0f"
    },
    {
        "Date":"2026-05-06",
        "Temperature_C":24.896191408,
        "Humidity_%":55.4467999912,
        "UV_Index":1.3315923705,
        "WindSpeed_m\/s":6.1926001946,
        "Rainfall_mm":2.0375992386,
        "Rain_Probability":18.5,
        "Rain_Alert":"No Rain \u2600\ufe0f"
    },
    {
        "Date":"2026-05-07",
        "Temperature_C":24.8970291823,
        "Humidity_%":55.4310947986,
        "UV_Index":1.3325144927,
        "WindSpeed_m\/s":6.1902358854,
        "Rainfall_mm":2.0104499328,
        "Rain_Probability":18.5,
        "Rain_Alert":"No Rain \u2600\ufe0f"
    },
    {
        "Date":"2026-05-08",
        "Temperature_C":24.8981693748,
        "Humidity_%":55.4317889805,
        "UV_Index":1.3322962348,
        "WindSpeed_m\/s":6.1899146106,
        "Rainfall_mm":2.0303419236,
        "Rain_Probability":18.5,
        "Rain_Alert":"No Rain \u2600\ufe0f"
    }
]