[
    {
        "Date":"2026-03-31",
        "Temperature_C":24.9968965683,
        "Humidity_%":55.3431336067,
        "UV_Index":1.3394801566,
        "WindSpeed_m\/s":6.2015004134,
        "Rainfall_mm":2.0435624077,
        "Rain_Probability":18.7,
        "Rain_Alert":"No Rain \u2600\ufe0f"
    },
    {
        "Date":"2026-04-01",
        "Temperature_C":25.0001354478,
        "Humidity_%":55.3374392495,
        "UV_Index":1.3403402432,
        "WindSpeed_m\/s":6.2032308189,
        "Rainfall_mm":2.0363026843,
        "Rain_Probability":18.7,
        "Rain_Alert":"No Rain \u2600\ufe0f"
    },
    {
        "Date":"2026-04-02",
        "Temperature_C":25.0003058582,
        "Humidity_%":55.3385570085,
        "UV_Index":1.3400190111,
        "WindSpeed_m\/s":6.2005653708,
        "Rainfall_mm":2.0433639246,
        "Rain_Probability":18.7,
        "Rain_Alert":"No Rain \u2600\ufe0f"
    },
    {
        "Date":"2026-04-03",
        "Temperature_C":25.00252733,
        "Humidity_%":55.3288194674,
        "UV_Index":1.3397076215,
        "WindSpeed_m\/s":6.205125435,
        "Rainfall_mm":2.0270111924,
        "Rain_Probability":18.7,
        "Rain_Alert":"No Rain \u2600\ufe0f"
    },
    {
        "Date":"2026-04-04",
        "Temperature_C":24.9983112646,
        "Humidity_%":55.3436571798,
        "UV_Index":1.3393311007,
        "WindSpeed_m\/s":6.2055179138,
        "Rainfall_mm":2.041524892,
        "Rain_Probability":18.7,
        "Rain_Alert":"No Rain \u2600\ufe0f"
    },
    {
        "Date":"2026-04-05",
        "Temperature_C":24.9990971541,
        "Humidity_%":55.3341091072,
        "UV_Index":1.3397972705,
        "WindSpeed_m\/s":6.2041332819,
        "Rainfall_mm":2.0357275386,
        "Rain_Probability":18.7,
        "Rain_Alert":"No Rain \u2600\ufe0f"
    },
    {
        "Date":"2026-04-06",
        "Temperature_C":24.9993542414,
        "Humidity_%":55.3328526151,
        "UV_Index":1.33983434,
        "WindSpeed_m\/s":6.2096150631,
        "Rainfall_mm":2.0430005229,
        "Rain_Probability":18.7,
        "Rain_Alert":"No Rain \u2600\ufe0f"
    }
]